{
  "__inputs": [
    {
      "name": "DS_PROMETHEUS",
      "label": "prometheus",
      "description": "",
      "type": "datasource",
      "pluginId": "prometheus",
      "pluginName": "Prometheus"
    }
  ],
  "__elements": {},
  "__requires": [
    {
      "type": "grafana",
      "id": "grafana",
      "name": "Grafana",
      "version": "12.0.0-85820"
    },
    {
      "type": "panel",
      "id": "piechart",
      "name": "Pie chart",
      "version": ""
    },
    {
      "type": "datasource",
      "id": "prometheus",
      "name": "Prometheus",
      "version": "1.0.0"
    },
    {
      "type": "panel",
      "id": "stat",
      "name": "Stat",
      "version": ""
    },
    {
      "type": "panel",
      "id": "table",
      "name": "Table",
      "version": ""
    },
    {
      "type": "panel",
      "id": "timeseries",
      "name": "Time series",
      "version": ""
    }
  ],
  "annotations": {
    "list": [
      {
        "builtIn": 1,
        "datasource": {
          "type": "grafana",
          "uid": "-- Grafana --"
        },
        "enable": true,
        "hide": true,
        "iconColor": "rgba(0, 211, 255, 1)",
        "name": "Annotations & Alerts",
        "type": "dashboard"
      }
    ]
  },
  "description": "The CompassVPN Dashboard offers real-time monitoring of VPN infrastructure, with server metrics, Xray traffic, and config management. Track resources, connections, bandwidth, and security in one place.",
  "editable": true,
  "fiscalYearStartMonth": 0,
  "graphTooltip": 0,
  "id": null,
  "links": [
    {
      "asDropdown": false,
      "icon": "external link",
      "includeVars": false,
      "keepTime": false,
      "tags": [],
      "targetBlank": true,
      "title": "CompassVPN Website",
      "tooltip": "CompassVPN Website",
      "type": "link",
      "url": "https://compassvpn.org"
    }
  ],
  "panels": [
    {
      "collapsed": false,
      "gridPos": {
        "h": 1,
        "w": 24,
        "x": 0,
        "y": 0
      },
      "id": 12,
      "panels": [],
      "title": "Overview",
      "type": "row"
    },
    {
      "datasource": {
        "type": "prometheus",
        "uid": "${DS_PROMETHEUS}"
      },
      "fieldConfig": {
        "defaults": {
          "color": {
            "mode": "palette-classic"
          },
          "custom": {
            "hideFrom": {
              "legend": false,
              "tooltip": false,
              "viz": false
            }
          },
          "mappings": [],
          "unit": "none"
        },
        "overrides": []
      },
      "gridPos": {
        "h": 12,
        "w": 3,
        "x": 0,
        "y": 1
      },
      "id": 27,
      "options": {
        "displayLabels": [
          "name",
          "value"
        ],
        "legend": {
          "displayMode": "table",
          "placement": "bottom",
          "showLegend": true,
          "values": [
            "value"
          ]
        },
        "pieType": "pie",
        "reduceOptions": {
          "calcs": [
            "lastNotNull"
          ],
          "fields": "",
          "values": false
        },
        "tooltip": {
          "hideZeros": false,
          "mode": "single",
          "sort": "none"
        }
      },
      "pluginVersion": "12.0.0-85820",
      "targets": [
        {
          "datasource": {
            "type": "prometheus",
            "uid": "${DS_PROMETHEUS}"
          },
          "editorMode": "code",
          "exemplar": false,
          "expr": "count((v2ray_up == 1) and ignoring(v2ray_up) v2ray_up)",
          "format": "time_series",
          "instant": false,
          "legendFormat": "Up",
          "range": true,
          "refId": "A"
        },
        {
          "datasource": {
            "type": "prometheus",
            "uid": "${DS_PROMETHEUS}"
          },
          "disableTextWrap": false,
          "editorMode": "code",
          "expr": "(count(v2ray_up) != 1) and ignoring(v2ray_up) v2ray_up",
          "fullMetaSearch": false,
          "hide": false,
          "includeNullMetadata": true,
          "instant": false,
          "legendFormat": "Down",
          "range": true,
          "refId": "B",
          "useBackend": false
        }
      ],
      "title": "Up / Down Instances",
      "type": "piechart"
    },
    {
      "datasource": {
        "type": "prometheus",
        "uid": "${DS_PROMETHEUS}"
      },
      "description": "List of all instances and their corresponding information within the time range.",
      "fieldConfig": {
        "defaults": {
          "color": {
            "fixedColor": "text",
            "mode": "fixed"
          },
          "custom": {
            "align": "center",
            "cellOptions": {
              "type": "auto",
              "wrapText": false
            },
            "inspect": true
          },
          "decimals": 1,
          "fieldMinMax": false,
          "mappings": [],
          "thresholds": {
            "mode": "absolute",
            "steps": [
              {
                "color": "green"
              }
            ]
          }
        },
        "overrides": [
          {
            "matcher": {
              "id": "byName",
              "options": "Value #A"
            },
            "properties": [
              {
                "id": "unit",
                "value": "s"
              },
              {
                "id": "decimals",
                "value": 1
              }
            ]
          },
          {
            "matcher": {
              "id": "byName",
              "options": "Value #B"
            },
            "properties": [
              {
                "id": "unit",
                "value": "decbytes"
              },
              {
                "id": "decimals",
                "value": 1
              }
            ]
          },
          {
            "matcher": {
              "id": "byName",
              "options": "Value #C"
            },
            "properties": [
              {
                "id": "unit",
                "value": "decbytes"
              },
              {
                "id": "decimals",
                "value": 1
              }
            ]
          },
          {
            "matcher": {
              "id": "byName",
              "options": "Total"
            },
            "properties": [
              {
                "id": "unit",
                "value": "decbytes"
              }
            ]
          }
        ]
      },
      "gridPos": {
        "h": 12,
        "w": 21,
        "x": 3,
        "y": 1
      },
      "id": 29,
      "options": {
        "cellHeight": "md",
        "footer": {
          "countRows": false,
          "enablePagination": false,
          "fields": [
            "Value #B",
            "Value #C",
            "Total"
          ],
          "reducer": [
            "sum"
          ],
          "show": true
        },
        "frameIndex": 0,
        "showHeader": true,
        "sortBy": [
          {
            "desc": true,
            "displayName": "Total"
          }
        ]
      },
      "pluginVersion": "12.0.0-85820",
      "targets": [
        {
          "datasource": {
            "type": "prometheus",
            "uid": "${DS_PROMETHEUS}"
          },
          "disableTextWrap": false,
          "editorMode": "code",
          "exemplar": false,
          "expr": "v2ray_uptime_seconds{donor=~\"$donor\", instance=~\"$instance\"}",
          "format": "table",
          "fullMetaSearch": false,
          "includeNullMetadata": false,
          "instant": true,
          "legendFormat": "__auto",
          "range": false,
          "refId": "A",
          "useBackend": false
        },
        {
          "datasource": {
            "type": "prometheus",
            "uid": "${DS_PROMETHEUS}"
          },
          "editorMode": "code",
          "exemplar": false,
          "expr": "sum by (instance) (increase(node_network_receive_bytes_total{donor=~\"$donor\", instance=~\"$instance\"}[$__range]))",
          "format": "table",
          "hide": false,
          "instant": true,
          "legendFormat": "__auto",
          "range": false,
          "refId": "B"
        },
        {
          "datasource": {
            "type": "prometheus",
            "uid": "${DS_PROMETHEUS}"
          },
          "editorMode": "code",
          "exemplar": false,
          "expr": "sum by (instance) (increase(node_network_transmit_bytes_total{donor=~\"$donor\", instance=~\"$instance\"}[$__range]))",
          "format": "table",
          "hide": false,
          "instant": true,
          "interval": "",
          "legendFormat": "__auto",
          "range": false,
          "refId": "C"
        }
      ],
      "title": "Overview",
      "transformations": [
        {
          "id": "joinByField",
          "options": {
            "byField": "instance",
            "mode": "outer"
          }
        },
        {
          "id": "organize",
          "options": {
            "excludeByName": {
              "Time 1": true,
              "Time 2": true,
              "Time 3": true,
              "Total": true,
              "__name__": true,
              "dimension 1": true,
              "dimension 2": true,
              "donor": false,
              "donor 1": false,
              "donor 2": true,
              "donor 3": true,
              "job": true,
              "job 1": true,
              "job 2": true,
              "job 3": true,
              "target 1": true,
              "target 2": true
            },
            "includeByName": {},
            "indexByName": {
              "Time 1": 2,
              "Time 2": 5,
              "Time 3": 7,
              "Value #A": 4,
              "Value #B": 6,
              "Value #C": 8,
              "__name__": 3,
              "donor": 0,
              "instance": 1,
              "job": 9
            },
            "renameByName": {
              "Value #A": "Uptime",
              "Value #B": "Downlink",
              "Value #C": "Uplink",
              "donor": "Donor",
              "donor 1": "",
              "instance": "Instance IP"
            }
          }
        },
        {
          "id": "calculateField",
          "options": {
            "alias": "Total",
            "binary": {
              "left": {
                "matcher": {
                  "id": "byName",
                  "options": "Uplink"
                }
              },
              "right": {
                "matcher": {
                  "id": "byName",
                  "options": "Downlink"
                }
              }
            },
            "mode": "binary",
            "reduce": {
              "include": [
                "Downlink",
                "Uplink"
              ],
              "reducer": "sum"
            },
            "replaceFields": false
          }
        },
        {
          "id": "filterByValue",
          "options": {
            "filters": [
              {
                "config": {
                  "id": "isNull",
                  "options": {}
                },
                "fieldName": "Donor"
              },
              {
                "config": {
                  "id": "isNull",
                  "options": {}
                },
                "fieldName": "Instance IP"
              }
            ],
            "match": "any",
            "type": "exclude"
          }
        }
      ],
      "type": "table"
    },
    {
      "datasource": {
        "type": "prometheus",
        "uid": "${DS_PROMETHEUS}"
      },
      "fieldConfig": {
        "defaults": {
          "color": {
            "mode": "shades"
          },
          "custom": {
            "axisBorderShow": false,
            "axisCenteredZero": false,
            "axisColorMode": "text",
            "axisLabel": "Total Bandwidth",
            "axisPlacement": "auto",
            "barAlignment": 0,
            "barWidthFactor": 0.6,
            "drawStyle": "line",
            "fillOpacity": 75,
            "gradientMode": "opacity",
            "hideFrom": {
              "legend": false,
              "tooltip": false,
              "viz": false
            },
            "insertNulls": false,
            "lineInterpolation": "smooth",
            "lineWidth": 1,
            "pointSize": 5,
            "scaleDistribution": {
              "type": "linear"
            },
            "showPoints": "auto",
            "spanNulls": false,
            "stacking": {
              "group": "A",
              "mode": "none"
            },
            "thresholdsStyle": {
              "mode": "off"
            }
          },
          "fieldMinMax": false,
          "links": [],
          "mappings": [],
          "thresholds": {
            "mode": "absolute",
            "steps": [
              {
                "color": "green"
              }
            ]
          },
          "unit": "Bps"
        },
        "overrides": [
          {
            "matcher": {
              "id": "byRegexp",
              "options": ".*Uplink.*"
            },
            "properties": [
              {
                "id": "custom.transform",
                "value": "negative-Y"
              },
              {
                "id": "color",
                "value": {
                  "fixedColor": "dark-yellow",
                  "mode": "shades"
                }
              }
            ]
          },
          {
            "matcher": {
              "id": "byRegexp",
              "options": ".*Downlink.*"
            },
            "properties": [
              {
                "id": "color",
                "value": {
                  "fixedColor": "dark-green",
                  "mode": "shades"
                }
              }
            ]
          }
        ]
      },
      "gridPos": {
        "h": 12,
        "w": 24,
        "x": 0,
        "y": 13
      },
      "id": 11,
      "options": {
        "legend": {
          "calcs": [
            "mean",
            "max",
            "lastNotNull"
          ],
          "displayMode": "table",
          "placement": "right",
          "showLegend": true,
          "sortBy": "Mean",
          "sortDesc": true
        },
        "tooltip": {
          "hideZeros": false,
          "mode": "multi",
          "sort": "none"
        }
      },
      "pluginVersion": "12.0.0-85820",
      "targets": [
        {
          "datasource": {
            "type": "prometheus",
            "uid": "${DS_PROMETHEUS}"
          },
          "disableTextWrap": false,
          "editorMode": "code",
          "exemplar": false,
          "expr": "sum by(instance) (irate(v2ray_traffic_downlink_bytes_total{donor=~\"$donor\", instance=~\"$instance\"}[10m]))",
          "format": "time_series",
          "fullMetaSearch": false,
          "hide": false,
          "includeNullMetadata": true,
          "instant": false,
          "interval": "",
          "legendFormat": "{{instance}} - Downlink",
          "range": true,
          "refId": "A",
          "useBackend": false
        },
        {
          "datasource": {
            "type": "prometheus",
            "uid": "${DS_PROMETHEUS}"
          },
          "disableTextWrap": false,
          "editorMode": "code",
          "exemplar": false,
          "expr": "sum by(instance) (irate(v2ray_traffic_uplink_bytes_total{donor=~\"$donor\", instance=~\"$instance\"}[10m]))",
          "fullMetaSearch": false,
          "hide": false,
          "includeNullMetadata": true,
          "interval": "",
          "legendFormat": "{{instance}} - Uplink",
          "range": true,
          "refId": "B",
          "useBackend": false
        }
      ],
      "title": "Total Bandwidth",
      "type": "timeseries"
    },
    {
      "collapsed": false,
      "gridPos": {
        "h": 1,
        "w": 24,
        "x": 0,
        "y": 25
      },
      "id": 8,
      "panels": [],
      "title": "Server Status",
      "type": "row"
    },
    {
      "datasource": {
        "type": "prometheus",
        "uid": "${DS_PROMETHEUS}"
      },
      "fieldConfig": {
        "defaults": {
          "color": {
            "mode": "palette-classic"
          },
          "custom": {
            "axisBorderShow": false,
            "axisCenteredZero": false,
            "axisColorMode": "text",
            "axisLabel": "",
            "axisPlacement": "auto",
            "barAlignment": 0,
            "barWidthFactor": 0.6,
            "drawStyle": "line",
            "fillOpacity": 75,
            "gradientMode": "opacity",
            "hideFrom": {
              "legend": false,
              "tooltip": false,
              "viz": false
            },
            "insertNulls": false,
            "lineInterpolation": "smooth",
            "lineStyle": {
              "fill": "solid"
            },
            "lineWidth": 1,
            "pointSize": 5,
            "scaleDistribution": {
              "type": "linear"
            },
            "showPoints": "auto",
            "spanNulls": false,
            "stacking": {
              "group": "A",
              "mode": "normal"
            },
            "thresholdsStyle": {
              "mode": "off"
            }
          },
          "decimals": 1,
          "mappings": [],
          "thresholds": {
            "mode": "absolute",
            "steps": [
              {
                "color": "green"
              },
              {
                "color": "red",
                "value": 80
              }
            ]
          },
          "unit": "percent"
        },
        "overrides": [
          {
            "matcher": {
              "id": "byRegexp",
              "options": ".*Idle.*"
            },
            "properties": [
              {
                "id": "custom.gradientMode",
                "value": "opacity"
              },
              {
                "id": "custom.fillOpacity",
                "value": 20
              },
              {
                "id": "color",
                "value": {
                  "fixedColor": "#ccccdb80",
                  "mode": "shades"
                }
              },
              {
                "id": "custom.lineWidth",
                "value": 0
              }
            ]
          }
        ]
      },
      "gridPos": {
        "h": 8,
        "w": 12,
        "x": 0,
        "y": 26
      },
      "id": 3,
      "options": {
        "legend": {
          "calcs": [
            "mean",
            "max",
            "lastNotNull"
          ],
          "displayMode": "table",
          "placement": "right",
          "showLegend": true,
          "sortBy": "Mean",
          "sortDesc": true
        },
        "tooltip": {
          "hideZeros": false,
          "mode": "multi",
          "sort": "desc"
        }
      },
      "pluginVersion": "12.0.0-85820",
      "targets": [
        {
          "datasource": {
            "type": "prometheus",
            "uid": "${DS_PROMETHEUS}"
          },
          "editorMode": "code",
          "expr": "sum by (instance)(rate(node_cpu_seconds_total{donor=~\"$donor\", instance=~\"$instance\", mode=\"system\"}[10m])) * 100",
          "format": "time_series",
          "hide": false,
          "intervalFactor": 1,
          "legendFormat": "{{instance}} - System",
          "range": true,
          "refId": "A"
        },
        {
          "datasource": {
            "type": "prometheus",
            "uid": "${DS_PROMETHEUS}"
          },
          "editorMode": "code",
          "expr": "sum by (instance)(rate(node_cpu_seconds_total{donor=~\"$donor\", instance=~\"$instance\", mode='user'}[10m])) * 100",
          "format": "time_series",
          "hide": false,
          "intervalFactor": 1,
          "legendFormat": "{{instance}} - User",
          "range": true,
          "refId": "B"
        },
        {
          "datasource": {
            "type": "prometheus",
            "uid": "${DS_PROMETHEUS}"
          },
          "editorMode": "code",
          "expr": "sum by (instance)(rate(node_cpu_seconds_total{donor=~\"$donor\", mode='iowait',instance=~\"$instance\"}[10m])) * 100",
          "format": "time_series",
          "hide": false,
          "intervalFactor": 1,
          "legendFormat": "{{instance}} - IOwait",
          "range": true,
          "refId": "C"
        },
        {
          "datasource": {
            "type": "prometheus",
            "uid": "${DS_PROMETHEUS}"
          },
          "editorMode": "code",
          "expr": "sum by (instance)(rate(node_cpu_seconds_total{donor=~\"$donor\", mode=~\".*irq\",instance=~\"$instance\"}[10m])) * 100",
          "format": "time_series",
          "hide": false,
          "intervalFactor": 1,
          "legendFormat": "{{instance}} - IRQ",
          "range": true,
          "refId": "D"
        },
        {
          "datasource": {
            "type": "prometheus",
            "uid": "${DS_PROMETHEUS}"
          },
          "editorMode": "code",
          "expr": "sum by (instance)(rate(node_cpu_seconds_total{donor=~\"$donor\", instance=~\"$instance\", mode!='idle',mode!='user',mode!='system',mode!='iowait',mode!='irq',mode!='softirq'}[10m])) * 100",
          "format": "time_series",
          "hide": false,
          "intervalFactor": 1,
          "legendFormat": "{{instance}} - Other",
          "range": true,
          "refId": "E"
        },
        {
          "datasource": {
            "type": "prometheus",
            "uid": "${DS_PROMETHEUS}"
          },
          "editorMode": "code",
          "expr": "sum by (instance)(rate(node_cpu_seconds_total{donor=~\"$donor\", mode='idle', instance=~\"$instance\"}[10m])) * 100",
          "format": "time_series",
          "hide": false,
          "intervalFactor": 1,
          "legendFormat": "{{instance}} - Idle",
          "range": true,
          "refId": "F"
        }
      ],
      "title": "CPU",
      "type": "timeseries"
    },
    {
      "datasource": {
        "type": "prometheus",
        "uid": "${DS_PROMETHEUS}"
      },
      "description": "Basic memory usage",
      "fieldConfig": {
        "defaults": {
          "color": {
            "mode": "palette-classic"
          },
          "custom": {
            "axisBorderShow": false,
            "axisCenteredZero": false,
            "axisColorMode": "text",
            "axisLabel": "",
            "axisPlacement": "auto",
            "barAlignment": 0,
            "barWidthFactor": 0.6,
            "drawStyle": "line",
            "fillOpacity": 50,
            "gradientMode": "opacity",
            "hideFrom": {
              "legend": false,
              "tooltip": false,
              "viz": false
            },
            "insertNulls": false,
            "lineInterpolation": "smooth",
            "lineWidth": 1,
            "pointSize": 5,
            "scaleDistribution": {
              "type": "linear"
            },
            "showPoints": "auto",
            "spanNulls": false,
            "stacking": {
              "group": "A",
              "mode": "normal"
            },
            "thresholdsStyle": {
              "mode": "off"
            }
          },
          "links": [],
          "mappings": [],
          "min": 0,
          "thresholds": {
            "mode": "absolute",
            "steps": [
              {
                "color": "green"
              },
              {
                "color": "red",
                "value": 80
              }
            ]
          },
          "unit": "bytes"
        },
        "overrides": [
          {
            "matcher": {
              "id": "byRegexp",
              "options": ".*Free.*"
            },
            "properties": [
              {
                "id": "color",
                "value": {
                  "fixedColor": "dark-green",
                  "mode": "fixed"
                }
              },
              {
                "id": "custom.fillOpacity",
                "value": 25
              }
            ]
          },
          {
            "matcher": {
              "id": "byRegexp",
              "options": ".*Buffer.*"
            },
            "properties": [
              {
                "id": "color",
                "value": {
                  "fixedColor": "dark-yellow",
                  "mode": "fixed"
                }
              }
            ]
          },
          {
            "matcher": {
              "id": "byRegexp",
              "options": ".*Used.*"
            },
            "properties": [
              {
                "id": "color",
                "value": {
                  "fixedColor": "dark-red",
                  "mode": "fixed"
                }
              }
            ]
          }
        ]
      },
      "gridPos": {
        "h": 8,
        "w": 12,
        "x": 12,
        "y": 26
      },
      "id": 28,
      "options": {
        "legend": {
          "calcs": [
            "mean",
            "max",
            "lastNotNull"
          ],
          "displayMode": "table",
          "placement": "right",
          "showLegend": true,
          "sortBy": "Mean",
          "sortDesc": true
        },
        "tooltip": {
          "hideZeros": false,
          "mode": "multi",
          "sort": "none"
        }
      },
      "pluginVersion": "12.0.0-85820",
      "targets": [
        {
          "datasource": {
            "type": "prometheus",
            "uid": "${datasource}"
          },
          "editorMode": "code",
          "expr": "node_memory_MemTotal_bytes{donor=~\"$donor\", instance=~\"$instance\"} - node_memory_MemFree_bytes{donor=~\"$donor\", instance=~\"$instance\"} - (node_memory_Cached_bytes{donor=~\"$donor\", instance=~\"$instance\"} + node_memory_Buffers_bytes{donor=~\"$donor\", instance=~\"$instance\"})",
          "format": "time_series",
          "hide": false,
          "intervalFactor": 1,
          "legendFormat": "{{instance}} - RAM Used",
          "range": true,
          "refId": "B",
          "step": 240
        },
        {
          "datasource": {
            "type": "prometheus",
            "uid": "${DS_PROMETHEUS}"
          },
          "editorMode": "code",
          "expr": "node_memory_Cached_bytes{donor=~\"$donor\", instance=~\"$instance\"} + node_memory_Buffers_bytes{donor=~\"$donor\", instance=~\"$instance\"}",
          "format": "time_series",
          "intervalFactor": 1,
          "legendFormat": "{{instance}} - RAM C+B",
          "range": true,
          "refId": "C",
          "step": 240
        },
        {
          "datasource": {
            "type": "prometheus",
            "uid": "${datasource}"
          },
          "editorMode": "code",
          "expr": "node_memory_MemFree_bytes{donor=~\"$donor\", instance=~\"$instance\"}",
          "format": "time_series",
          "hide": false,
          "intervalFactor": 1,
          "legendFormat": "{{instance}} - RAM Free",
          "range": true,
          "refId": "D",
          "step": 240
        }
      ],
      "title": "Memory Basic",
      "type": "timeseries"
    },
    {
      "datasource": {
        "type": "prometheus",
        "uid": "${DS_PROMETHEUS}"
      },
      "fieldConfig": {
        "defaults": {
          "color": {
            "mode": "palette-classic"
          },
          "custom": {
            "axisBorderShow": false,
            "axisCenteredZero": false,
            "axisColorMode": "text",
            "axisLabel": "",
            "axisPlacement": "auto",
            "barAlignment": 0,
            "barWidthFactor": 0.6,
            "drawStyle": "line",
            "fillOpacity": 50,
            "gradientMode": "opacity",
            "hideFrom": {
              "legend": false,
              "tooltip": false,
              "viz": false
            },
            "insertNulls": false,
            "lineInterpolation": "smooth",
            "lineWidth": 1,
            "pointSize": 5,
            "scaleDistribution": {
              "type": "linear"
            },
            "showPoints": "auto",
            "spanNulls": false,
            "stacking": {
              "group": "A",
              "mode": "none"
            },
            "thresholdsStyle": {
              "mode": "off"
            }
          },
          "decimals": 0,
          "mappings": [],
          "thresholds": {
            "mode": "absolute",
            "steps": [
              {
                "color": "green"
              }
            ]
          },
          "unit": "Bps"
        },
        "overrides": [
          {
            "matcher": {
              "id": "byRegexp",
              "options": ".*Transmit.*"
            },
            "properties": [
              {
                "id": "color",
                "value": {
                  "fixedColor": "dark-yellow",
                  "mode": "shades"
                }
              }
            ]
          },
          {
            "matcher": {
              "id": "byRegexp",
              "options": ".*Receive.*"
            },
            "properties": [
              {
                "id": "color",
                "value": {
                  "fixedColor": "dark-green",
                  "mode": "shades"
                }
              }
            ]
          }
        ]
      },
      "gridPos": {
        "h": 8,
        "w": 12,
        "x": 0,
        "y": 34
      },
      "id": 5,
      "options": {
        "legend": {
          "calcs": [
            "mean",
            "max",
            "lastNotNull"
          ],
          "displayMode": "table",
          "placement": "right",
          "showLegend": true,
          "sortBy": "Mean",
          "sortDesc": true
        },
        "tooltip": {
          "hideZeros": false,
          "mode": "multi",
          "sort": "none"
        }
      },
      "pluginVersion": "12.0.0-85820",
      "targets": [
        {
          "datasource": {
            "type": "prometheus",
            "uid": "${DS_PROMETHEUS}"
          },
          "disableTextWrap": false,
          "editorMode": "code",
          "expr": "irate(node_network_receive_bytes_total{donor=~\"$donor\", instance=~\"$instance\"}[10m]) > 1024",
          "format": "time_series",
          "fullMetaSearch": false,
          "hide": false,
          "includeNullMetadata": true,
          "intervalFactor": 1,
          "legendFormat": "{{instance}} - {{device}} - Receive",
          "range": true,
          "refId": "B",
          "useBackend": false
        },
        {
          "datasource": {
            "type": "prometheus",
            "uid": "${DS_PROMETHEUS}"
          },
          "disableTextWrap": false,
          "editorMode": "code",
          "expr": "irate(node_network_transmit_bytes_total{donor=~\"$donor\", instance=~\"$instance\"}[10m]) > 1024",
          "format": "time_series",
          "fullMetaSearch": false,
          "hide": false,
          "includeNullMetadata": true,
          "intervalFactor": 1,
          "legendFormat": "{{instance}} - {{device}} - Transmit",
          "range": true,
          "refId": "C",
          "useBackend": false
        }
      ],
      "title": "Network",
      "type": "timeseries"
    },
    {
      "datasource": {
        "type": "prometheus",
        "uid": "${DS_PROMETHEUS}"
      },
      "fieldConfig": {
        "defaults": {
          "color": {
            "mode": "fixed"
          },
          "custom": {
            "axisBorderShow": false,
            "axisCenteredZero": false,
            "axisColorMode": "text",
            "axisLabel": "",
            "axisPlacement": "auto",
            "barAlignment": 0,
            "barWidthFactor": 0.6,
            "drawStyle": "line",
            "fillOpacity": 25,
            "gradientMode": "opacity",
            "hideFrom": {
              "legend": false,
              "tooltip": false,
              "viz": false
            },
            "insertNulls": false,
            "lineInterpolation": "smooth",
            "lineStyle": {
              "fill": "solid"
            },
            "lineWidth": 1,
            "pointSize": 5,
            "scaleDistribution": {
              "type": "linear"
            },
            "showPoints": "auto",
            "spanNulls": false,
            "stacking": {
              "group": "A",
              "mode": "none"
            },
            "thresholdsStyle": {
              "mode": "off"
            }
          },
          "decimals": 1,
          "mappings": [],
          "min": 0,
          "thresholds": {
            "mode": "absolute",
            "steps": [
              {
                "color": "green"
              },
              {
                "color": "red",
                "value": 80
              }
            ]
          },
          "unit": "decbytes"
        },
        "overrides": [
          {
            "matcher": {
              "id": "byRegexp",
              "options": ".*Total.*"
            },
            "properties": [
              {
                "id": "color",
                "value": {
                  "fixedColor": "dark-green",
                  "mode": "fixed"
                }
              }
            ]
          },
          {
            "matcher": {
              "id": "byRegexp",
              "options": ".*Used.*"
            },
            "properties": [
              {
                "id": "color",
                "value": {
                  "fixedColor": "dark-red",
                  "mode": "fixed"
                }
              },
              {
                "id": "custom.fillOpacity",
                "value": 75
              }
            ]
          }
        ]
      },
      "gridPos": {
        "h": 8,
        "w": 12,
        "x": 12,
        "y": 34
      },
      "id": 6,
      "options": {
        "legend": {
          "calcs": [
            "lastNotNull"
          ],
          "displayMode": "table",
          "placement": "right",
          "showLegend": true,
          "sortBy": "Last *",
          "sortDesc": true
        },
        "tooltip": {
          "hideZeros": false,
          "mode": "single",
          "sort": "none"
        }
      },
      "pluginVersion": "12.0.0-85820",
      "targets": [
        {
          "datasource": {
            "type": "prometheus",
            "uid": "${DS_PROMETHEUS}"
          },
          "editorMode": "code",
          "expr": "node_filesystem_size_bytes{donor=~\"$donor\", instance=~\"$instance\", device!~'rootfs', mountpoint='/'} - node_filesystem_avail_bytes{donor=~\"$donor\", instance=~\"$instance\",device!~'rootfs', mountpoint='/'}",
          "format": "time_series",
          "intervalFactor": 1,
          "legendFormat": "{{instance}} - Used",
          "range": true,
          "refId": "A"
        },
        {
          "datasource": {
            "type": "prometheus",
            "uid": "${DS_PROMETHEUS}"
          },
          "editorMode": "code",
          "expr": "node_filesystem_size_bytes{donor=~\"$donor\", instance=~\"$instance\", device!~'rootfs', mountpoint='/'}",
          "format": "time_series",
          "intervalFactor": 1,
          "legendFormat": "{{instance}} - Total",
          "range": true,
          "refId": "B"
        }
      ],
      "title": "Disk Usage",
      "type": "timeseries"
    },
    {
      "datasource": {
        "type": "prometheus",
        "uid": "${DS_PROMETHEUS}"
      },
      "description": "Total Network Usage for each instance and its network interface.",
      "fieldConfig": {
        "defaults": {
          "color": {
            "fixedColor": "#ccccdb80",
            "mode": "fixed"
          },
          "decimals": 1,
          "fieldMinMax": false,
          "mappings": [],
          "thresholds": {
            "mode": "absolute",
            "steps": [
              {
                "color": "green"
              }
            ]
          },
          "unit": "decbytes"
        },
        "overrides": [
          {
            "matcher": {
              "id": "byRegexp",
              "options": ".*Total.*"
            },
            "properties": [
              {
                "id": "color",
                "value": {
                  "fixedColor": "dark-blue",
                  "mode": "shades"
                }
              }
            ]
          },
          {
            "matcher": {
              "id": "byRegexp",
              "options": ".*Transmit.*"
            },
            "properties": [
              {
                "id": "color",
                "value": {
                  "fixedColor": "dark-green",
                  "mode": "shades"
                }
              }
            ]
          },
          {
            "matcher": {
              "id": "byRegexp",
              "options": ".*Receive.*"
            },
            "properties": [
              {
                "id": "color",
                "value": {
                  "fixedColor": "dark-yellow",
                  "mode": "shades"
                }
              }
            ]
          }
        ]
      },
      "gridPos": {
        "h": 11,
        "w": 24,
        "x": 0,
        "y": 42
      },
      "id": 30,
      "options": {
        "colorMode": "value",
        "graphMode": "area",
        "justifyMode": "center",
        "orientation": "auto",
        "percentChangeColorMode": "same_as_value",
        "reduceOptions": {
          "calcs": [
            "lastNotNull"
          ],
          "fields": "",
          "values": false
        },
        "showPercentChange": false,
        "textMode": "auto",
        "wideLayout": true
      },
      "pluginVersion": "12.0.0-85820",
      "targets": [
        {
          "datasource": {
            "type": "prometheus",
            "uid": "${DS_PROMETHEUS}"
          },
          "disableTextWrap": false,
          "editorMode": "code",
          "exemplar": false,
          "expr": "sum by(instance) (\r\n  increase(node_network_receive_bytes_total{donor=~\"$donor\", instance=~\"$instance\"}[$__range]) +\r\n  increase(node_network_transmit_bytes_total{donor=~\"$donor\", instance=~\"$instance\"}[$__range])\r\n) > 100000000\r\n",
          "fullMetaSearch": false,
          "hide": false,
          "includeNullMetadata": true,
          "instant": false,
          "legendFormat": "{{instance}} - Total",
          "range": true,
          "refId": "A",
          "useBackend": false
        },
        {
          "datasource": {
            "type": "prometheus",
            "uid": "${DS_PROMETHEUS}"
          },
          "disableTextWrap": false,
          "editorMode": "code",
          "exemplar": false,
          "expr": "increase(node_network_receive_bytes_total{donor=~\"$donor\", instance=~\"$instance\"}[$__range]) > 100000000",
          "format": "time_series",
          "fullMetaSearch": false,
          "includeNullMetadata": false,
          "instant": false,
          "intervalFactor": 1,
          "legendFormat": "{{instance}} - {{device}} - Transmit",
          "range": true,
          "refId": "B",
          "useBackend": false
        },
        {
          "datasource": {
            "type": "prometheus",
            "uid": "${DS_PROMETHEUS}"
          },
          "disableTextWrap": false,
          "editorMode": "code",
          "exemplar": false,
          "expr": "increase(node_network_transmit_bytes_total{donor=~\"$donor\", instance=~\"$instance\"}[$__range]) > 100000000",
          "format": "time_series",
          "fullMetaSearch": false,
          "includeNullMetadata": false,
          "instant": false,
          "intervalFactor": 1,
          "legendFormat": "{{instance}} - {{device}} - Receive",
          "range": true,
          "refId": "C",
          "useBackend": false
        }
      ],
      "title": "Total Network Usage",
      "type": "stat"
    },
    {
      "collapsed": false,
      "gridPos": {
        "h": 1,
        "w": 24,
        "x": 0,
        "y": 53
      },
      "id": 9,
      "panels": [],
      "title": "XRAY Metrics",
      "type": "row"
    },
    {
      "datasource": {
        "type": "prometheus",
        "uid": "${DS_PROMETHEUS}"
      },
      "description": "Upload Speed of each Inbound",
      "fieldConfig": {
        "defaults": {
          "color": {
            "mode": "fixed"
          },
          "custom": {
            "axisBorderShow": false,
            "axisCenteredZero": false,
            "axisColorMode": "text",
            "axisLabel": "",
            "axisPlacement": "auto",
            "barAlignment": 0,
            "barWidthFactor": 0.6,
            "drawStyle": "line",
            "fillOpacity": 50,
            "gradientMode": "opacity",
            "hideFrom": {
              "legend": false,
              "tooltip": false,
              "viz": false
            },
            "insertNulls": false,
            "lineInterpolation": "smooth",
            "lineWidth": 1,
            "pointSize": 5,
            "scaleDistribution": {
              "type": "linear"
            },
            "showPoints": "never",
            "spanNulls": false,
            "stacking": {
              "group": "A",
              "mode": "none"
            },
            "thresholdsStyle": {
              "mode": "off"
            }
          },
          "links": [],
          "mappings": [],
          "thresholds": {
            "mode": "absolute",
            "steps": [
              {
                "color": "green"
              }
            ]
          },
          "unit": "Bps"
        },
        "overrides": [
          {
            "matcher": {
              "id": "byRegexp",
              "options": ".*tcp.*"
            },
            "properties": [
              {
                "id": "color",
                "value": {
                  "fixedColor": "dark-green",
                  "mode": "shades"
                }
              }
            ]
          },
          {
            "matcher": {
              "id": "byRegexp",
              "options": ".*hu.*"
            },
            "properties": [
              {
                "id": "color",
                "value": {
                  "fixedColor": "dark-blue",
                  "mode": "shades"
                }
              }
            ]
          },
          {
            "matcher": {
              "id": "byRegexp",
              "options": ".*xhttp.*"
            },
            "properties": [
              {
                "id": "color",
                "value": {
                  "fixedColor": "dark-yellow",
                  "mode": "shades"
                }
              }
            ]
          }
        ]
      },
      "gridPos": {
        "h": 10,
        "w": 12,
        "x": 0,
        "y": 54
      },
      "id": 14,
      "options": {
        "legend": {
          "calcs": [
            "mean",
            "max",
            "lastNotNull"
          ],
          "displayMode": "table",
          "placement": "right",
          "showLegend": true,
          "sortBy": "Mean",
          "sortDesc": true
        },
        "tooltip": {
          "hideZeros": false,
          "mode": "multi",
          "sort": "none"
        }
      },
      "pluginVersion": "12.0.0-85820",
      "targets": [
        {
          "datasource": {
            "type": "prometheus",
            "uid": "${DS_PROMETHEUS}"
          },
          "disableTextWrap": false,
          "editorMode": "code",
          "expr": "irate(v2ray_traffic_uplink_bytes_total{donor=~\"$donor\", instance=~\"$instance\", dimension=~\"inbound\", target!=\"doko\"}[10m])",
          "fullMetaSearch": false,
          "includeNullMetadata": true,
          "interval": "",
          "legendFormat": "{{instance}} - {{target}}",
          "range": true,
          "refId": "A",
          "useBackend": false
        }
      ],
      "title": "Upload Speed of Inbounds",
      "type": "timeseries"
    },
    {
      "datasource": {
        "type": "prometheus",
        "uid": "${DS_PROMETHEUS}"
      },
      "description": "Download Speed of each Inbound",
      "fieldConfig": {
        "defaults": {
          "color": {
            "fixedColor": "text",
            "mode": "fixed"
          },
          "custom": {
            "axisBorderShow": false,
            "axisCenteredZero": false,
            "axisColorMode": "text",
            "axisLabel": "",
            "axisPlacement": "auto",
            "barAlignment": 0,
            "barWidthFactor": 0.6,
            "drawStyle": "line",
            "fillOpacity": 50,
            "gradientMode": "opacity",
            "hideFrom": {
              "legend": false,
              "tooltip": false,
              "viz": false
            },
            "insertNulls": false,
            "lineInterpolation": "smooth",
            "lineWidth": 1,
            "pointSize": 5,
            "scaleDistribution": {
              "type": "linear"
            },
            "showPoints": "never",
            "spanNulls": false,
            "stacking": {
              "group": "A",
              "mode": "none"
            },
            "thresholdsStyle": {
              "mode": "off"
            }
          },
          "links": [],
          "mappings": [],
          "thresholds": {
            "mode": "absolute",
            "steps": [
              {
                "color": "green"
              }
            ]
          },
          "unit": "Bps"
        },
        "overrides": [
          {
            "matcher": {
              "id": "byRegexp",
              "options": ".*tcp.*"
            },
            "properties": [
              {
                "id": "color",
                "value": {
                  "fixedColor": "dark-green",
                  "mode": "shades"
                }
              }
            ]
          },
          {
            "matcher": {
              "id": "byRegexp",
              "options": ".*hu.*"
            },
            "properties": [
              {
                "id": "color",
                "value": {
                  "fixedColor": "dark-blue",
                  "mode": "shades"
                }
              }
            ]
          },
          {
            "matcher": {
              "id": "byRegexp",
              "options": ".*xhttp.*"
            },
            "properties": [
              {
                "id": "color",
                "value": {
                  "fixedColor": "dark-yellow",
                  "mode": "shades"
                }
              }
            ]
          }
        ]
      },
      "gridPos": {
        "h": 10,
        "w": 12,
        "x": 12,
        "y": 54
      },
      "id": 13,
      "options": {
        "legend": {
          "calcs": [
            "mean",
            "max",
            "lastNotNull"
          ],
          "displayMode": "table",
          "placement": "right",
          "showLegend": true,
          "sortBy": "Mean",
          "sortDesc": true
        },
        "tooltip": {
          "hideZeros": false,
          "mode": "multi",
          "sort": "none"
        }
      },
      "pluginVersion": "12.0.0-85820",
      "targets": [
        {
          "datasource": {
            "type": "prometheus",
            "uid": "${DS_PROMETHEUS}"
          },
          "disableTextWrap": false,
          "editorMode": "code",
          "expr": "irate(v2ray_traffic_downlink_bytes_total{donor=~\"$donor\", instance=~\"$instance\", dimension=~\"inbound\", target!=\"doko\"}[10m])",
          "fullMetaSearch": false,
          "includeNullMetadata": true,
          "interval": "",
          "legendFormat": "{{instance}} - {{target}}",
          "range": true,
          "refId": "A",
          "useBackend": false
        }
      ],
      "title": "Download Speed of Inbounds",
      "type": "timeseries"
    },
    {
      "datasource": {
        "type": "prometheus",
        "uid": "${DS_PROMETHEUS}"
      },
      "description": "Number of unique users actively connected to the server. (Approximately)",
      "fieldConfig": {
        "defaults": {
          "color": {
            "fixedColor": "dark-green",
            "mode": "shades"
          },
          "custom": {
            "axisBorderShow": false,
            "axisCenteredZero": false,
            "axisColorMode": "text",
            "axisLabel": "",
            "axisPlacement": "auto",
            "barAlignment": 0,
            "barWidthFactor": 0.6,
            "drawStyle": "line",
            "fillOpacity": 50,
            "gradientMode": "opacity",
            "hideFrom": {
              "legend": false,
              "tooltip": false,
              "viz": false
            },
            "insertNulls": false,
            "lineInterpolation": "smooth",
            "lineWidth": 1,
            "pointSize": 5,
            "scaleDistribution": {
              "type": "linear"
            },
            "showPoints": "auto",
            "spanNulls": true,
            "stacking": {
              "group": "A",
              "mode": "none"
            },
            "thresholdsStyle": {
              "mode": "off"
            }
          },
          "mappings": [],
          "thresholds": {
            "mode": "absolute",
            "steps": [
              {
                "color": "#2ecc71"
              }
            ]
          },
          "unit": "short"
        },
        "overrides": []
      },
      "gridPos": {
        "h": 9,
        "w": 19,
        "x": 0,
        "y": 64
      },
      "id": 15,
      "options": {
        "legend": {
          "calcs": [
            "mean",
            "max",
            "lastNotNull"
          ],
          "displayMode": "table",
          "placement": "bottom",
          "showLegend": true,
          "sortBy": "Mean",
          "sortDesc": true
        },
        "tooltip": {
          "hideZeros": false,
          "mode": "single",
          "sort": "none"
        }
      },
      "pluginVersion": "12.0.0-85820",
      "targets": [
        {
          "datasource": {
            "type": "prometheus",
            "uid": "${DS_PROMETHEUS}"
          },
          "editorMode": "code",
          "expr": "xray_unique_users{donor=~\"$donor\", instance=~\"$instance\"}",
          "legendFormat": "{{instance}} - {{donor}}",
          "range": true,
          "refId": "A"
        }
      ],
      "title": "Active Unique Users",
      "type": "timeseries"
    },
    {
      "datasource": {
        "type": "prometheus",
        "uid": "${DS_PROMETHEUS}"
      },
      "description": "Approximation of current unique users for the last 2 minutes.",
      "fieldConfig": {
        "defaults": {
          "color": {
            "fixedColor": "dark-green",
            "mode": "shades"
          },
          "decimals": 0,
          "mappings": [],
          "thresholds": {
            "mode": "absolute",
            "steps": [
              {
                "color": "#2ecc71"
              }
            ]
          },
          "unit": "short"
        },
        "overrides": []
      },
      "gridPos": {
        "h": 9,
        "w": 5,
        "x": 19,
        "y": 64
      },
      "id": 18,
      "options": {
        "colorMode": "value",
        "graphMode": "area",
        "justifyMode": "center",
        "orientation": "auto",
        "percentChangeColorMode": "same_as_value",
        "reduceOptions": {
          "calcs": [
            "lastNotNull"
          ],
          "fields": "",
          "values": false
        },
        "showPercentChange": false,
        "textMode": "value_and_name",
        "wideLayout": true
      },
      "pluginVersion": "12.0.0-85820",
      "targets": [
        {
          "datasource": {
            "type": "prometheus",
            "uid": "${DS_PROMETHEUS}"
          },
          "editorMode": "code",
          "expr": "xray_unique_users{donor=~\"$donor\", instance=~\"$instance\"}",
          "legendFormat": "{{instance}}",
          "range": true,
          "refId": "A"
        }
      ],
      "title": "Current Unique Users",
      "type": "stat"
    },
    {
      "datasource": {
        "type": "prometheus",
        "uid": "${DS_PROMETHEUS}"
      },
      "description": "Total number of connections established over time. This includes all connection attempts, including reconnections.",
      "fieldConfig": {
        "defaults": {
          "color": {
            "fixedColor": "dark-blue",
            "mode": "shades"
          },
          "custom": {
            "axisBorderShow": false,
            "axisCenteredZero": false,
            "axisColorMode": "text",
            "axisLabel": "",
            "axisPlacement": "auto",
            "barAlignment": 0,
            "barWidthFactor": 0.6,
            "drawStyle": "line",
            "fillOpacity": 50,
            "gradientMode": "opacity",
            "hideFrom": {
              "legend": false,
              "tooltip": false,
              "viz": false
            },
            "insertNulls": false,
            "lineInterpolation": "smooth",
            "lineWidth": 1,
            "pointSize": 5,
            "scaleDistribution": {
              "type": "linear"
            },
            "showPoints": "auto",
            "spanNulls": true,
            "stacking": {
              "group": "A",
              "mode": "none"
            },
            "thresholdsStyle": {
              "mode": "off"
            }
          },
          "mappings": [],
          "thresholds": {
            "mode": "absolute",
            "steps": [
              {
                "color": "#3498db"
              }
            ]
          },
          "unit": "short"
        },
        "overrides": []
      },
      "gridPos": {
        "h": 9,
        "w": 19,
        "x": 0,
        "y": 73
      },
      "id": 16,
      "options": {
        "legend": {
          "calcs": [
            "mean",
            "max",
            "lastNotNull"
          ],
          "displayMode": "table",
          "placement": "bottom",
          "showLegend": true,
          "sortBy": "Mean",
          "sortDesc": true
        },
        "tooltip": {
          "hideZeros": false,
          "mode": "single",
          "sort": "none"
        }
      },
      "pluginVersion": "12.0.0-85820",
      "targets": [
        {
          "datasource": {
            "type": "prometheus",
            "uid": "${DS_PROMETHEUS}"
          },
          "editorMode": "code",
          "expr": "xray_total_connections{donor=~\"$donor\", instance=~\"$instance\"}",
          "legendFormat": "{{instance}} - {{donor}}",
          "range": true,
          "refId": "A"
        }
      ],
      "title": "Total Connection Count",
      "type": "timeseries"
    },
    {
      "datasource": {
        "type": "prometheus",
        "uid": "${DS_PROMETHEUS}"
      },
      "fieldConfig": {
        "defaults": {
          "color": {
            "fixedColor": "dark-blue",
            "mode": "shades"
          },
          "decimals": 1,
          "mappings": [],
          "thresholds": {
            "mode": "absolute",
            "steps": [
              {
                "color": "#3498db"
              }
            ]
          },
          "unit": "short"
        },
        "overrides": []
      },
      "gridPos": {
        "h": 9,
        "w": 5,
        "x": 19,
        "y": 73
      },
      "id": 19,
      "options": {
        "colorMode": "value",
        "graphMode": "area",
        "justifyMode": "center",
        "orientation": "auto",
        "percentChangeColorMode": "same_as_value",
        "reduceOptions": {
          "calcs": [
            "lastNotNull"
          ],
          "fields": "",
          "values": false
        },
        "showPercentChange": false,
        "textMode": "auto",
        "wideLayout": true
      },
      "pluginVersion": "12.0.0-85820",
      "targets": [
        {
          "datasource": {
            "type": "prometheus",
            "uid": "${DS_PROMETHEUS}"
          },
          "editorMode": "code",
          "expr": "xray_total_connections{donor=~\"$donor\", instance=~\"$instance\"}",
          "legendFormat": "{{instance}}",
          "range": true,
          "refId": "A"
        }
      ],
      "title": "Current Total Connections",
      "type": "stat"
    },
    {
      "datasource": {
        "type": "prometheus",
        "uid": "${DS_PROMETHEUS}"
      },
      "description": "Average number of connections per unique user.",
      "fieldConfig": {
        "defaults": {
          "color": {
            "fixedColor": "#917400",
            "mode": "shades"
          },
          "custom": {
            "axisBorderShow": false,
            "axisCenteredZero": false,
            "axisColorMode": "text",
            "axisLabel": "",
            "axisPlacement": "auto",
            "barAlignment": 0,
            "barWidthFactor": 0.6,
            "drawStyle": "line",
            "fillOpacity": 50,
            "gradientMode": "opacity",
            "hideFrom": {
              "legend": false,
              "tooltip": false,
              "viz": false
            },
            "insertNulls": false,
            "lineInterpolation": "smooth",
            "lineWidth": 1,
            "pointSize": 5,
            "scaleDistribution": {
              "type": "linear"
            },
            "showPoints": "auto",
            "spanNulls": true,
            "stacking": {
              "group": "A",
              "mode": "none"
            },
            "thresholdsStyle": {
              "mode": "off"
            }
          },
          "mappings": [],
          "thresholds": {
            "mode": "absolute",
            "steps": [
              {
                "color": "#00FFFF"
              }
            ]
          },
          "unit": "short"
        },
        "overrides": []
      },
      "gridPos": {
        "h": 9,
        "w": 19,
        "x": 0,
        "y": 82
      },
      "id": 17,
      "options": {
        "legend": {
          "calcs": [
            "mean",
            "max",
            "lastNotNull"
          ],
          "displayMode": "table",
          "placement": "bottom",
          "showLegend": true,
          "sortBy": "Mean",
          "sortDesc": true
        },
        "tooltip": {
          "hideZeros": false,
          "mode": "single",
          "sort": "none"
        }
      },
      "pluginVersion": "12.0.0-85820",
      "targets": [
        {
          "datasource": {
            "type": "prometheus",
            "uid": "${DS_PROMETHEUS}"
          },
          "editorMode": "code",
          "expr": "xray_total_connections{donor=~\"$donor\", instance=~\"$instance\"} / xray_unique_users{donor=~\"$donor\", instance=~\"$instance\"}",
          "legendFormat": "{{instance}} - {{donor}}",
          "range": true,
          "refId": "A"
        }
      ],
      "title": "Connections per User",
      "type": "timeseries"
    },
    {
      "datasource": {
        "type": "prometheus",
        "uid": "${DS_PROMETHEUS}"
      },
      "fieldConfig": {
        "defaults": {
          "color": {
            "fixedColor": "#917400",
            "mode": "fixed"
          },
          "decimals": 0,
          "mappings": [],
          "thresholds": {
            "mode": "absolute",
            "steps": [
              {
                "color": "#00FFFF"
              }
            ]
          },
          "unit": "none"
        },
        "overrides": []
      },
      "gridPos": {
        "h": 9,
        "w": 5,
        "x": 19,
        "y": 82
      },
      "id": 20,
      "options": {
        "colorMode": "value",
        "graphMode": "area",
        "justifyMode": "center",
        "orientation": "auto",
        "percentChangeColorMode": "standard",
        "reduceOptions": {
          "calcs": [
            "lastNotNull"
          ],
          "fields": "",
          "values": false
        },
        "showPercentChange": false,
        "textMode": "auto",
        "wideLayout": true
      },
      "pluginVersion": "12.0.0-85820",
      "targets": [
        {
          "datasource": {
            "type": "prometheus",
            "uid": "${DS_PROMETHEUS}"
          },
          "editorMode": "code",
          "expr": "xray_total_connections{donor=~\"$donor\", instance=~\"$instance\"} / xray_unique_users{donor=~\"$donor\", instance=~\"$instance\"}",
          "legendFormat": "{{instance}}",
          "range": true,
          "refId": "A"
        }
      ],
      "title": "Current Connections per User",
      "type": "stat"
    },
    {
      "collapsed": false,
      "gridPos": {
        "h": 1,
        "w": 24,
        "x": 0,
        "y": 91
      },
      "id": 21,
      "panels": [],
      "title": "XRAY Routing Rules",
      "type": "row"
    },
    {
      "datasource": {
        "type": "prometheus",
        "uid": "${DS_PROMETHEUS}"
      },
      "description": "Number of requests blocked by routing rules over time period.",
      "fieldConfig": {
        "defaults": {
          "color": {
            "fixedColor": "dark-red",
            "mode": "shades"
          },
          "custom": {
            "axisBorderShow": false,
            "axisCenteredZero": false,
            "axisColorMode": "text",
            "axisLabel": "",
            "axisPlacement": "auto",
            "barAlignment": 0,
            "barWidthFactor": 0.6,
            "drawStyle": "line",
            "fillOpacity": 50,
            "gradientMode": "opacity",
            "hideFrom": {
              "legend": false,
              "tooltip": false,
              "viz": false
            },
            "insertNulls": false,
            "lineInterpolation": "smooth",
            "lineWidth": 1,
            "pointSize": 5,
            "scaleDistribution": {
              "type": "linear"
            },
            "showPoints": "auto",
            "spanNulls": true,
            "stacking": {
              "group": "A",
              "mode": "none"
            },
            "thresholdsStyle": {
              "mode": "off"
            }
          },
          "decimals": 0,
          "mappings": [],
          "thresholds": {
            "mode": "absolute",
            "steps": [
              {
                "color": "#e74c3c"
              }
            ]
          },
          "unit": "short"
        },
        "overrides": []
      },
      "gridPos": {
        "h": 10,
        "w": 9,
        "x": 0,
        "y": 92
      },
      "id": 22,
      "options": {
        "legend": {
          "calcs": [
            "mean",
            "max",
            "lastNotNull"
          ],
          "displayMode": "table",
          "placement": "bottom",
          "showLegend": true,
          "sortBy": "Mean",
          "sortDesc": true
        },
        "tooltip": {
          "hideZeros": false,
          "mode": "single",
          "sort": "none"
        }
      },
      "pluginVersion": "12.0.0-85820",
      "targets": [
        {
          "datasource": {
            "type": "prometheus",
            "uid": "${DS_PROMETHEUS}"
          },
          "editorMode": "code",
          "expr": "xray_blocked_requests{donor=~\"$donor\", instance=~\"$instance\"}",
          "legendFormat": "{{instance}} - {{donor}}",
          "range": true,
          "refId": "A"
        }
      ],
      "title": "Blocked Requests",
      "type": "timeseries"
    },
    {
      "datasource": {
        "type": "prometheus",
        "uid": "${DS_PROMETHEUS}"
      },
      "description": "Percentage of requests that are blocked by routing rules.",
      "fieldConfig": {
        "defaults": {
          "color": {
            "fixedColor": "dark-red",
            "mode": "shades"
          },
          "decimals": 1,
          "mappings": [],
          "thresholds": {
            "mode": "absolute",
            "steps": [
              {
                "color": "#e74c3c"
              }
            ]
          },
          "unit": "percent"
        },
        "overrides": []
      },
      "gridPos": {
        "h": 10,
        "w": 6,
        "x": 9,
        "y": 92
      },
      "id": 23,
      "options": {
        "colorMode": "value",
        "graphMode": "area",
        "justifyMode": "center",
        "orientation": "auto",
        "percentChangeColorMode": "standard",
        "reduceOptions": {
          "calcs": [
            "lastNotNull"
          ],
          "fields": "",
          "values": false
        },
        "showPercentChange": false,
        "textMode": "auto",
        "wideLayout": true
      },
      "pluginVersion": "12.0.0-85820",
      "targets": [
        {
          "datasource": {
            "type": "prometheus",
            "uid": "${DS_PROMETHEUS}"
          },
          "editorMode": "code",
          "expr": "xray_blocked_percentage{donor=~\"$donor\", instance=~\"$instance\"}",
          "legendFormat": "{{instance}}",
          "range": true,
          "refId": "A"
        }
      ],
      "title": "Blocked Requests Percentage",
      "type": "stat"
    },
    {
      "datasource": {
        "type": "prometheus",
        "uid": "${DS_PROMETHEUS}"
      },
      "fieldConfig": {
        "defaults": {
          "color": {
            "fixedColor": "text",
            "mode": "fixed"
          },
          "custom": {
            "hideFrom": {
              "legend": false,
              "tooltip": false,
              "viz": false
            }
          },
          "decimals": 1,
          "fieldMinMax": false,
          "mappings": [],
          "unit": "short"
        },
        "overrides": [
          {
            "matcher": {
              "id": "byRegexp",
              "options": ".*Allowed.*"
            },
            "properties": [
              {
                "id": "color",
                "value": {
                  "fixedColor": "dark-green",
                  "mode": "shades"
                }
              }
            ]
          },
          {
            "matcher": {
              "id": "byRegexp",
              "options": ".*Blocked.*"
            },
            "properties": [
              {
                "id": "color",
                "value": {
                  "fixedColor": "dark-red",
                  "mode": "shades"
                }
              }
            ]
          }
        ]
      },
      "gridPos": {
        "h": 10,
        "w": 9,
        "x": 15,
        "y": 92
      },
      "id": 24,
      "options": {
        "displayLabels": [
          "name",
          "value",
          "percent"
        ],
        "legend": {
          "displayMode": "table",
          "placement": "right",
          "showLegend": true,
          "sortBy": "Percent",
          "sortDesc": false,
          "values": [
            "percent",
            "value"
          ]
        },
        "pieType": "pie",
        "reduceOptions": {
          "calcs": [
            "lastNotNull"
          ],
          "fields": "",
          "values": false
        },
        "tooltip": {
          "hideZeros": false,
          "mode": "single",
          "sort": "none"
        }
      },
      "pluginVersion": "12.0.0-85820",
      "targets": [
        {
          "datasource": {
            "type": "prometheus",
            "uid": "${DS_PROMETHEUS}"
          },
          "editorMode": "code",
          "expr": "xray_total_connections{donor=~\"$donor\", instance=~\"$instance\"} - xray_blocked_requests{donor=~\"$donor\", instance=~\"$instance\"}",
          "hide": false,
          "legendFormat": "{{instance}} - Allowed",
          "range": true,
          "refId": "B"
        },
        {
          "datasource": {
            "type": "prometheus",
            "uid": "${DS_PROMETHEUS}"
          },
          "editorMode": "code",
          "expr": "xray_blocked_requests{donor=~\"$donor\", instance=~\"$instance\"}",
          "legendFormat": "{{instance}} - Blocked",
          "range": true,
          "refId": "A"
        }
      ],
      "title": "Request Distribution",
      "type": "piechart"
    },
    {
      "collapsed": false,
      "gridPos": {
        "h": 1,
        "w": 24,
        "x": 0,
        "y": 102
      },
      "id": 25,
      "panels": [],
      "title": "VPN Configurations",
      "type": "row"
    },
    {
      "datasource": {
        "type": "prometheus",
        "uid": "${DS_PROMETHEUS}"
      },
      "fieldConfig": {
        "defaults": {
          "color": {
            "fixedColor": "text",
            "mode": "fixed"
          },
          "custom": {
            "align": "center",
            "cellOptions": {
              "type": "auto"
            },
            "inspect": true
          },
          "mappings": [],
          "thresholds": {
            "mode": "absolute",
            "steps": [
              {
                "color": "green"
              },
              {
                "color": "red",
                "value": 80
              }
            ]
          }
        },
        "overrides": [
          {
            "matcher": {
              "id": "byName",
              "options": "Delay (ms)"
            },
            "properties": [
              {
                "id": "custom.cellOptions",
                "value": {
                  "mode": "lcd",
                  "type": "gauge",
                  "valueDisplayMode": "color"
                }
              },
              {
                "id": "color",
                "value": {
                  "mode": "continuous-GrYlRd"
                }
              },
              {
                "id": "mappings",
                "value": [
                  {
                    "options": {
                      "-1": {
                        "color": "dark-red",
                        "index": 0,
                        "text": "DOWN"
                      }
                    },
                    "type": "value"
                  }
                ]
              }
            ]
          },
          {
            "matcher": {
              "id": "byName",
              "options": "Transport"
            },
            "properties": [
              {
                "id": "custom.width",
                "value": 200
              }
            ]
          },
          {
            "matcher": {
              "id": "byName",
              "options": "Port"
            },
            "properties": [
              {
                "id": "custom.width",
                "value": 150
              }
            ]
          },
          {
            "matcher": {
              "id": "byName",
              "options": "Country"
            },
            "properties": [
              {
                "id": "custom.width",
                "value": 100
              }
            ]
          },
          {
            "matcher": {
              "id": "byName",
              "options": "Instance IP"
            },
            "properties": [
              {
                "id": "custom.width",
                "value": 150
              }
            ]
          },
          {
            "matcher": {
              "id": "byName",
              "options": "Delay (ms)"
            },
            "properties": [
              {
                "id": "custom.width",
                "value": 300
              }
            ]
          }
        ]
      },
      "gridPos": {
        "h": 16,
        "w": 24,
        "x": 0,
        "y": 103
      },
      "id": 26,
      "options": {
        "cellHeight": "sm",
        "footer": {
          "countRows": true,
          "enablePagination": false,
          "fields": "",
          "reducer": [],
          "show": false
        },
        "showHeader": true,
        "sortBy": [
          {
            "desc": false,
            "displayName": "Delay (ms)"
          }
        ]
      },
      "pluginVersion": "12.0.0-85820",
      "targets": [
        {
          "datasource": {
            "type": "prometheus",
            "uid": "${DS_PROMETHEUS}"
          },
          "disableTextWrap": false,
          "editorMode": "code",
          "exemplar": false,
          "expr": "vpn_config{donor=~\"$donor\", instance=~\"$instance\"}",
          "format": "table",
          "fullMetaSearch": false,
          "includeNullMetadata": true,
          "instant": true,
          "interval": "",
          "legendFormat": "__auto",
          "range": false,
          "refId": "A",
          "useBackend": false
        }
      ],
      "title": "VPN Configuration Links",
      "transformations": [
        {
          "id": "organize",
          "options": {
            "excludeByName": {
              "Time": true,
              "__name__": true,
              "config_protocol": true,
              "config_security": true,
              "donor": true,
              "ip": true,
              "job": true,
              "machine_id": true,
              "region": true
            },
            "includeByName": {},
            "indexByName": {
              "Time": 0,
              "Value": 15,
              "__name__": 1,
              "config_host": 4,
              "config_link": 2,
              "config_port": 5,
              "config_protocol": 6,
              "config_security": 7,
              "config_type": 3,
              "country": 8,
              "donor": 9,
              "instance": 10,
              "ip": 11,
              "job": 12,
              "machine_id": 13,
              "region": 14
            },
            "renameByName": {
              "Value": "Delay (ms)",
              "config_host": "Host Domain",
              "config_link": "Config Link",
              "config_port": "Port",
              "config_type": "Transport",
              "country": "Country",
              "instance": "Instance IP"
            }
          }
        }
      ],
      "type": "table"
    }
  ],
  "refresh": "5m",
  "schemaVersion": 41,
  "tags": [
    "compassvpn"
  ],
  "templating": {
    "list": [
      {
        "allowCustomValue": false,
        "current": {},
        "definition": "label_values(donor)",
        "description": "",
        "includeAll": true,
        "label": "Donor",
        "name": "donor",
        "options": [],
        "query": {
          "qryType": 1,
          "query": "label_values(donor)",
          "refId": "PrometheusVariableQueryEditor-VariableQuery"
        },
        "refresh": 1,
        "regex": "",
        "type": "query"
      },
      {
        "current": {},
        "hide": 2,
        "label": "Datasource",
        "name": "datasource",
        "options": [],
        "query": "prometheus",
        "refresh": 1,
        "regex": "",
        "type": "datasource"
      },
      {
        "allowCustomValue": false,
        "current": {},
        "definition": "query_result(topk(100, increase(node_network_receive_bytes_total[1d])))",
        "includeAll": true,
        "label": "Instance",
        "name": "instance",
        "options": [],
        "query": {
          "qryType": 3,
          "query": "query_result(topk(100, increase(node_network_receive_bytes_total[1d])))",
          "refId": "PrometheusVariableQueryEditor-VariableQuery"
        },
        "refresh": 1,
        "regex": "/instance=\"([^\"]+)\"/",
        "type": "query"
      }
    ]
  },
  "time": {
    "from": "now-2d",
    "to": "now"
  },
  "timepicker": {
    "refresh_intervals": [
      "1m",
      "5m",
      "15m",
      "30m",
      "1h",
      "2h",
      "4h",
      "12h",
      "1d"
    ]
  },
  "timezone": "browser",
  "title": "CompassVPN Dashboard",
  "uid": "compassvpnorgdashboard",
  "version": 6,
  "weekStart": ""
}
